{
  "articleContent": "<div>\n<div data-page-id=\"LFjddntmYomdVkxIRL5ci4U5nhh\" data-docx-has-block-data=\"false\">\n<p class=\"ace-line ace-line old-record-id-ZmmNdnljboVlEFxNvVocbD1DnPf\"><img style=\"display: block; margin-left: auto; margin-right: auto;\" src=\"https://hw-media-cdn-mingchao.kurogame.com/object/1719849600000/olczthfz88wnx0euqm-1719898681928.jpg\" alt=\"\" width=\"800\" height=\"450\" /></p>\n<p class=\"ace-line ace-line old-record-id-ZmmNdnljboVlEFxNvVocbD1DnPf\">&nbsp;</p>\n<p class=\"ace-line ace-line old-record-id-ZmmNdnljboVlEFxNvVocbD1DnPf\"><strong><span style=\"font-family: 微软雅黑; font-size: 14pt;\">✦Event Duration✦</span></strong><br /><br /><span style=\"font-family: 微软雅黑; font-size: 14pt;\">07/04 10:00 - 08/05 03:59 (Server Time)</span></p>\n<p class=\"ace-line ace-line old-record-id-ZmmNdnljboVlEFxNvVocbD1DnPf\"><br /><strong><span style=\"font-family: 微软雅黑; font-size: 14pt;\">✦Eligibility✦</span></strong><br /><br /><span style=\"font-family: 微软雅黑; font-size: 14pt;\">Reach Union Level 17</span></p>\n<p class=\"ace-line ace-line old-record-id-ZmmNdnljboVlEFxNvVocbD1DnPf\"><br /><strong><span style=\"font-family: 微软雅黑; font-size: 14pt;\">✦Rewards✦</span></strong><br /><br /><span style=\"font-family: 微软雅黑; font-size: 14pt;\">Astrite x1000, Malleable Elite Class Echo I x1, Malleable Elite Class Echo II x1, Premium Tuner x360, Premium Sealed Tube x36 and other development materials.</span></p>\n<p class=\"ace-line ace-line old-record-id-ZmmNdnljboVlEFxNvVocbD1DnPf\">&nbsp;</p>\n<p class=\"ace-line ace-line old-record-id-ZmmNdnljboVlEFxNvVocbD1DnPf\"><span style=\"font-family: 微软雅黑; font-size: 14pt;\"><img style=\"display: block; margin-left: auto; margin-right: auto;\" src=\"https://hw-media-cdn-mingchao.kurogame.com/object/1719849600000/ovf3tfwyfjfpmlf68o-1719931075187.jpg\" alt=\"\" width=\"800\" height=\"5587\" /><br /></span></p>\n<p class=\"ace-line ace-line old-record-id-ZmmNdnljboVlEFxNvVocbD1DnPf\">&nbsp;</p>\n<p class=\"ace-line ace-line old-record-id-ZmmNdnljboVlEFxNvVocbD1DnPf\">&nbsp;</p>\n<p class=\"ace-line ace-line old-record-id-ZmmNdnljboVlEFxNvVocbD1DnPf\">&nbsp;</p>\n<p class=\"ace-line ace-line old-record-id-ZmmNdnljboVlEFxNvVocbD1DnPf\">&nbsp;</p>\n</div>\n</div>",
  "articleCover": "",
  "articleId": 1025,
  "articleTitle": "New Content \"Dreams Ablaze in Darkness\" Coming Soon!",
  "articleType": 57,
  "articleTypeName": "News",
  "contentCover": "",
  "gameId": "G152-en",
  "startTime": "2024-07-02 15:00:00",
  "articleDesc": "",
  "createTime": "2024-07-02 13:39:01",
  "suggestCover": "",
  "top": 0
}