{
  "articleContent": "<p><span style=\"font-family: 微软雅黑; font-size: 14pt;\">The archipelago cannot be accessed from any known lands. Only those recognized by the Black Shores or who have received an invitation and guidance can navigate their way to this hidden place.</span></p>\n<p>&nbsp;</p>\n<p><img style=\"display: block; margin-left: auto; margin-right: auto;\" src=\"https://hw-media-cdn-mingchao.kurogame.com/object/1727193600000/u3t97qclkseay5jz9z-1727234277004.jpg\" alt=\"\" width=\"800\" height=\"10302\" /></p>\n<p>&nbsp;</p>\n<p>&nbsp;</p>",
  "articleId": 1365,
  "articleTitle": "Wutherium Geographic: Lands and Waters — The Black Shores Vol. 1",
  "articleType": 58,
  "articleTypeName": "Notice",
  "endTime": "2099-01-01 00:00:00",
  "gameId": "G152-en",
  "startTime": "2024-09-25 12:00:00"
}
