{
  "articleContent": "<div><img style=\"display: block; margin-left: auto; margin-right: auto;\" src=\"https://hw-media-cdn-mingchao.kurogame.com/akiwebsite/website2.0/images/1731081600000/vjhmyp8ybgarhbonto-1731115129687.jpg\" alt=\"\" width=\"802\" height=\"451\"><img style=\"display: block; margin-left: auto; margin-right: auto;\" src=\"https://hw-media-cdn-mingchao.kurogame.com/akiwebsite/website2.0/images/1731081600000/k82hmxw5nzjcylwerz-1731115161451.jpg\" alt=\"\" width=\"801\" height=\"3475\"><img style=\"display: block; margin-left: auto; margin-right: auto;\" src=\"https://hw-media-cdn-mingchao.kurogame.com/akiwebsite/website2.0/images/1731081600000/3ztr7a902791cmhmx0-1731115181028.jpg\" alt=\"\" width=\"800\" height=\"8745\"><img style=\"display: block; margin-left: auto; margin-right: auto;\" src=\"https://hw-media-cdn-mingchao.kurogame.com/akiwebsite/website2.0/images/1731081600000/oprvic65k01xnw9k8a-1731115199349.jpg\" alt=\"\" width=\"800\" height=\"8547\"><img style=\"display: block; margin-left: auto; margin-right: auto;\" src=\"https://hw-media-cdn-mingchao.kurogame.com/akiwebsite/website2.0/images/1731254400000/un6d3jptzxkteygbde-1731295622843.jpg\" alt=\"\" width=\"800\" height=\"2450\"></div>",
  "articleCover": "",
  "articleId": 1607,
  "articleTitle": "Wuthering Waves Update Preview | Version 1.4 \"When the Night Knocks\" to be released on Nov 14th",
  "articleType": 58,
  "articleTypeName": "Notice",
  "contentCover": "",
  "gameId": "G152-en",
  "startTime": "2024-11-10 11:00:00",
  "articleDesc": "",
  "createTime": "2024-11-09 09:20:35",
  "sortingMark": 133,
  "suggestCover": "",
  "top": 0
}