{
  "articleContent": "<div><img style=\"display: block; margin-left: auto; margin-right: auto;\" src=\"https://hw-media-cdn-mingchao.kurogame.com/object/1757606400000/9q5plqmum2keg23ly8-1757671258356.jpg\" width=\"800\" height=\"1422\" data-media-source=\"production_G152_en\" data-desc=\"succ\"><img style=\"display: block; margin-left: auto; margin-right: auto;\" src=\"https://hw-media-cdn-mingchao.kurogame.com/object/1757606400000/9utnkpyec0wnxtjece-1757671282337.jpg\" width=\"800\" height=\"1556\" data-media-source=\"production_G152_en\" data-desc=\"succ\"><img style=\"display: block; margin-left: auto; margin-right: auto;\" src=\"https://hw-media-cdn-mingchao.kurogame.com/object/1757606400000/6nesvev441n5qsejh0-1757671306570.gif\" width=\"800\" height=\"1332\" data-media-source=\"production_G152_en\" data-desc=\"succ\"><img style=\"display: block; margin-left: auto; margin-right: auto;\" src=\"https://hw-media-cdn-mingchao.kurogame.com/object/1757606400000/acep5v2jvyw4ki6a80-1757671324294.gif\" width=\"800\" data-media-source=\"production_G152_en\" data-desc=\"succ\"><img style=\"display: block; margin-left: auto; margin-right: auto;\" src=\"https://hw-media-cdn-mingchao.kurogame.com/object/1757606400000/3xoif6jw2typqa5sew-1757671342966.gif\" width=\"800\" data-media-source=\"production_G152_en\" data-desc=\"succ\"><img style=\"display: block; margin-left: auto; margin-right: auto;\" src=\"https://hw-media-cdn-mingchao.kurogame.com/object/1757606400000/ma2celvhczpmvhgiop-1757671362193.gif\" width=\"800\" height=\"1768\" data-media-source=\"production_G152_en\" data-desc=\"succ\"><img style=\"display: block; margin-left: auto; margin-right: auto;\" src=\"https://hw-media-cdn-mingchao.kurogame.com/object/1757606400000/gyjs9pbgejrlrcye96-1757671390391.gif\" width=\"800\" height=\"1081\" data-media-source=\"production_G152_en\" data-desc=\"succ\"><img style=\"display: block; margin-left: auto; margin-right: auto;\" src=\"https://hw-media-cdn-mingchao.kurogame.com/object/1757606400000/vbiw1wx56hd6e1y23b-1757671406325.gif\" width=\"800\" height=\"1083\" data-media-source=\"production_G152_en\" data-desc=\"succ\"><img style=\"display: block; margin-left: auto; margin-right: auto;\" src=\"https://hw-media-cdn-mingchao.kurogame.com/object/1757606400000/3tyn4zm5ksesefpa9k-1757671415803.jpg\" width=\"800\" height=\"5848\" data-media-source=\"production_G152_en\" data-desc=\"succ\"></div>",
  "articleId": 3252,
  "articleTitle": "Profile Reveal | Stasis, Cycle, Renewal — Iuno",
  "articleType": 58,
  "articleTypeName": "Notice",
  "endTime": "2099-01-01 00:00:00",
  "gameId": "G152-en",
  "startTime": "2025-09-13 11:05:00",
  "articleDesc": "",
  "createTime": "2025-09-12 18:04:11",
  "suggestCover": "",
  "top": 0
}